ypmp_example/__init__.py
ypmp_example/functions.py
ypmp_example/py.typed
ypmp_example-0.2.0.dist-info/WHEEL
ypmp_example-0.2.0.dist-info/METADATA
ypmp_example-0.2.0.dist-info/RECORD
